{
    "Network": {
        "view": ["Administrator", "PLM", "R&D", "TPM", "NWCC", "viewer"],
        "add": ["Administrator", "PLM", "R&D", "TPM", "NWCC"],
        "edit": ["Administrator", "PLM", "R&D", "TPM", "NWCC"],
        "del": ["Administrator", "PLM", "R&D", "TPM", "NWCC"],
        "export": ["Administrator", "PLM", "R&D", "TPM", "NWCC", "viewer"]
    },
    "Product": {
        "view": ["Administrator", "PLM", "R&D", "TPM", "NWCC", "viewer"],
        "add": ["Administrator", "PLM", "R&D", "TPM", "NWCC"],
        "edit": ["Administrator", "PLM", "R&D", "TPM", "NWCC"],
        "del": ["Administrator", "PLM", "R&D", "TPM", "NWCC"],
        "export": ["Administrator", "PLM", "R&D", "TPM", "NWCC", "viewer"]
    },
    "Financial": {
        "view": ["Administrator", "PLM", "R&D", "TPM", "NWCC", "viewer"],
        "add": ["Administrator", "PLM", "R&D", "TPM", "NWCC"],
        "edit": ["Administrator", "PLM", "R&D", "TPM", "NWCC"],
        "del": ["Administrator", "PLM", "R&D", "TPM", "NWCC"],
        "export": ["Administrator", "PLM", "R&D", "TPM", "NWCC", "viewer"]
    },
    "Contacts": {
        "view": ["Administrator", "PLM", "R&D", "TPM", "NWCC", "viewer"],
        "edit": ["Administrator", "PLM", "R&D", "TPM", "NWCC"],
        "export": ["Administrator", "PLM", "R&D", "TPM", "NWCC", "viewer"]
    },
    "Shipment": {
        "export": ["Administrator", "PLM", "R&D", "TPM", "NWCC", "viewer"]
    },
    "Soft": {
        "export": ["Administrator", "PLM", "R&D", "TPM", "NWCC", "viewer"]
    },
    "RCR": {
        "export": ["Administrator", "PLM", "R&D", "TPM", "NWCC", "viewer"]
    },
    "MyView": {
        "view": ["Administrator", "PLM", "R&D", "TPM", "NWCC", "viewer"],
        "free-add": [],
        "free-del": [],
        "free-detail": []
    },
    "MyAction": {
        "view": ["Administrator", "PLM", "R&D", "TPM", "NWCC", "viewer"],
        "export": []
    },
    "CustomerReport": {
        "view": ["Administrator", "PLM", "R&D", "TPM", "NWCC", "viewer"]
    },
    "ManufactorySW": {
        "view": ["Administrator", "PLM", "R&D", "TPM", "NWCC", "viewer"],
        "SWDetail": [],
        "export": ["Administrator", "PLM", "R&D", "TPM", "NWCC", "viewer"]
    },
    "TrainReleaseSW": {
        "view": ["Administrator", "PLM", "R&D", "TPM", "NWCC", "viewer"]
    },
    "MainStreamOverview": {
        "view": ["Administrator", "PLM", "R&D", "TPM", "NWCC", "viewer"]
    },
    "ONTSoftware": {
        "add": [],
        "edit": ["Administrator"],
        "export": ["Administrator", "PLM", "R&D", "TPM", "NWCC", "viewer"]
    },
    "NWFSoftware": {
        "add": [],
        "edit": ["Administrator"],
        "export": ["Administrator", "PLM", "R&D", "TPM", "NWCC", "viewer"]
    },
    "MobileAppSoftware": {
        "add": [],
        "edit": ["Administrator"],
        "export": ["Administrator", "PLM", "R&D", "TPM", "NWCC", "viewer"]
    },
    "NWCCSoftware": {
        "add": [],
        "edit": ["Administrator"],
        "export": ["Administrator", "PLM", "R&D", "TPM", "NWCC", "viewer"]
    },
    "FWASoftware": {
        "add": [],
        "edit": ["Administrator"],
        "export": ["Administrator", "PLM", "R&D", "TPM", "NWCC", "viewer"]
    },
    "GoldenInfo": {
        "view": ["Administrator", "PLM", "R&D", "TPM", "NWCC", "viewer"],
        "add": ["Administrator"],
        "edit": ["Administrator"],
        "del": ["Administrator"],
        "export": ["Administrator", "PLM", "R&D", "TPM", "NWCC", "viewer"]
    },
    "SoftwareOverview": {
        "view": ["Administrator", "PLM", "R&D", "TPM", "NWCC", "viewer"],
        "add": ["Administrator"],
        "edit": ["Administrator"],
        "del": ["Administrator"],
        "export": ["Administrator", "PLM", "R&D", "TPM", "NWCC", "viewer"]
    },
    "ProductStatus": {
        "view": ["Administrator", "PLM", "R&D", "TPM", "NWCC", "viewer"],
        "export": ["Administrator", "PLM", "R&D", "TPM", "NWCC", "viewer"]
    },
    "FocRequest": {
        "view": ["Administrator", "PLM", "R&D", "TPM", "NWCC", "viewer"],
        "export": ["Administrator", "PLM", "R&D", "TPM", "NWCC", "viewer"]
    },
    "NWCCSaaS": {
        "view": ["Administrator", "PLM", "R&D", "TPM", "NWCC", "viewer"],
        "add": ["Administrator"],
        "edit": ["Administrator"],
        "del": ["Administrator"],
        "export": ["Administrator", "PLM", "R&D", "TPM", "NWCC", "viewer"]
    },
    "PreConfig": {
        "view": ["Administrator", "PLM", "R&D", "TPM", "NWCC", "viewer"], 
        "add": ["PLM","R&D"],
        "edit": ["PLM","R&D"],
        "del": ["PLM","R&D"],  
        "export": ["Administrator", "PLM", "R&D", "TPM", "NWCC"]
    },
    "DeltaConfig": {
        "view": ["Administrator", "PLM", "R&D", "TPM", "NWCC", "viewer"],
        "add": ["Administrator", "PLM", "R&D", "TPM", "NWCC"],
        "edit": ["Administrator", "PLM", "R&D", "TPM", "NWCC"],
        "del": ["Administrator", "PLM", "R&D", "TPM", "NWCC"],
        "export": ["Administrator", "PLM", "R&D", "TPM", "NWCC", "viewer"]
    },
    "TargetCustomer": {
        "view": ["Administrator", "PLM", "R&D", "TPM", "NWCC", "viewer"],
        "export": ["Administrator", "PLM", "R&D", "TPM", "NWCC", "viewer"]
    },
    "TargetDevice": {
        "view": ["Administrator", "PLM", "R&D", "TPM", "NWCC", "viewer"],
        "export": ["Administrator", "PLM", "R&D", "TPM", "NWCC", "viewer"]
    },
    "EndToEnd": {
        "view": ["Administrator", "PLM", "R&D", "TPM", "NWCC", "viewer"],
        "edit": ["Administrator", "PLM", "R&D", "TPM", "NWCC"],
        "mailReview": ["Administrator"],
        "mailRemind": ["Administrator"],
        "export": ["Administrator", "PLM", "R&D", "TPM", "NWCC", "viewer"]
    },
    "SalesForce": {
        "view": ["Administrator", "PLM", "R&D", "TPM", "NWCC", "viewer"],
        "export": ["Administrator", "PLM", "R&D", "TPM", "NWCC", "viewer"]
    },
    "UserManagement": {
        "view": ["Administrator"],
        "add": ["Administrator"],
        "edit": ["Administrator"],
        "export": ["Administrator", "PLM", "R&D", "TPM", "NWCC", "viewer"]
    },
    "GradeManagement": {
        "view": ["Administrator"],
        "add": ["Administrator"],
        "edit": ["Administrator"],
        "export": ["Administrator", "PLM", "R&D", "TPM", "NWCC", "viewer"]
    },
    "home": {
        "view": []
    }

}